pyms_nist_search/NISTMS_min.H
pyms_nist_search/pyms_nist_search.c
pyms_nist_search/mona_tools.py
pyms_nist_search/__init__.pyi
pyms_nist_search/win_engine.py
pyms_nist_search/base.py
pyms_nist_search/NISTERR.H
pyms_nist_search/utils.py
pyms_nist_search/reference_data.py
pyms_nist_search/__init__.py
pyms_nist_search/search_result.py
pyms_nist_search/py.typed
pyms_nist_search/NISTMS.H
pyms_nist_search/pyms_nist_search_min.c
pyms_nist_search/_core.cpython-38-x86_64-linux-gnu.so
pyms_nist_search/docker_engine.py
pyms_nist_search/x64/nistdl64.lib
pyms_nist_search/x64/nistdl64_2gb.dll
pyms_nist_search/x64/ctnt66_64.dll
pyms_nist_search/x64/nistdl64_2gb.lib
pyms_nist_search/x64/nistdl64.dll
pyms_nist_search/x86/nistdl32_2gb.dll
pyms_nist_search/x86/nistdl32_2gb.lib
pyms_nist_search/x86/nistdl32.dll
pyms_nist_search/x86/ctnt66.dll
pyms_nist_search/x86/nistdl32.lib
pyms_nist_search/templates/__init__.py
pyms_nist_search/templates/msp_template
pyms_nist_search-0.8.0.dist-info/top_level.txt
pyms_nist_search-0.8.0.dist-info/LICENSE
pyms_nist_search-0.8.0.dist-info/WHEEL
pyms_nist_search-0.8.0.dist-info/RECORD
pyms_nist_search-0.8.0.dist-info/METADATA
