Metadata-Version: 2.1
Name: pyms-nist-search
Version: 0.8.0
Summary: PyMassSpec extension for searching mass spectra using NIST's Mass Spectrum Search Engine.
Home-page: https://github.com/domdfcoding/pynist
Author: Dominic Davis-Foster
Author-email: Dominic Davis-Foster <dominic@davis-foster.co.uk>
License:                    GNU LESSER GENERAL PUBLIC LICENSE
Project-URL: Homepage, https://github.com/domdfcoding/pynist
Project-URL: Issue Tracker, https://github.com/domdfcoding/pynist/issues
Project-URL: Source Code, https://github.com/domdfcoding/pynist
Project-URL: Documentation, https://pynist.readthedocs.io/en/latest
Platform: Windows
Platform: macOS
Platform: Linux
Classifier: Development Status :: 4 - Beta
Classifier: Intended Audience :: Developers
Classifier: Intended Audience :: Science/Research
Classifier: License :: OSI Approved :: GNU Lesser General Public License v3 or later (LGPLv3+)
Classifier: Operating System :: Microsoft :: Windows
Classifier: Operating System :: Microsoft :: Windows :: Windows 7
Classifier: Operating System :: Microsoft :: Windows :: Windows 8.1
Classifier: Operating System :: Microsoft :: Windows :: Windows 10
Classifier: Operating System :: POSIX :: Linux
Classifier: Programming Language :: C
Classifier: Programming Language :: Python
Classifier: Programming Language :: Python :: 3 :: Only
Classifier: Programming Language :: Python :: 3.7
Classifier: Programming Language :: Python :: 3.8
Classifier: Programming Language :: Python :: 3.9
Classifier: Programming Language :: Python :: 3.10
Classifier: Programming Language :: Python :: 3.11
Classifier: Programming Language :: Python :: 3.12
Classifier: Programming Language :: Python :: Implementation :: CPython
Classifier: Topic :: Scientific/Engineering :: Chemistry
Classifier: Topic :: Software Development :: Libraries :: Python Modules
Classifier: Topic :: Utilities
Classifier: Typing :: Typed
Requires-Python: >=3.7
License-File: LICENSE
